soundscapy/__init__.py
soundscapy/_optionals.py
soundscapy/logging.py
soundscapy/audio/__init__.py
soundscapy/audio/analysis_settings.py
soundscapy/audio/audio_analysis.py
soundscapy/audio/binaural.py
soundscapy/audio/metrics.py
soundscapy/audio/parallel_processing.py
soundscapy/data/ISD v1.0 Data.csv
soundscapy/data/__init__.py
soundscapy/data/default_settings.yaml
soundscapy/databases/__init__.py
soundscapy/databases/araus.py
soundscapy/databases/isd.py
soundscapy/databases/satp.py
soundscapy/plotting/__init__.py
soundscapy/plotting/backends.py
soundscapy/plotting/circumplex_plot.py
soundscapy/plotting/likert.py
soundscapy/plotting/plot_functions.py
soundscapy/plotting/plotting_utils.py
soundscapy/plotting/stylers.py
soundscapy/surveys/__init__.py
soundscapy/surveys/processing.py
soundscapy/surveys/survey_utils.py
soundscapy-0.7.8.dist-info/METADATA
soundscapy-0.7.8.dist-info/WHEEL
soundscapy-0.7.8.dist-info/licenses/LICENSE
soundscapy-0.7.8.dist-info/RECORD
