Metadata-Version: 2.4
Name: soundscapy
Version: 0.7.8
Summary: A python library for analysing and visualising soundscape assessments.
Project-URL: repository, https://github.com/MitchellAcoustics/Soundscapy
Project-URL: documentation, https://soundscapy.readthedocs.io/en/latest/
Author-email: Andrew Mitchell <a.j.mitchell@ucl.ac.uk>
License: BSD-3-Clause
License-File: LICENSE
Keywords: acoustics,audio analysis,psychoacoustics,soundscape
Classifier: License :: OSI Approved :: BSD License
Classifier: Operating System :: OS Independent
Classifier: Programming Language :: Python :: 3
Requires-Python: >=3.10
Requires-Dist: loguru>=0.7.2
Requires-Dist: numpy!=1.26
Requires-Dist: pandas[excel]>=2.2.2
Requires-Dist: plotly>=5.23.0
Requires-Dist: pydantic>=2.8.2
Requires-Dist: pyyaml>=6.0.2
Requires-Dist: scipy>=1.14.1
Requires-Dist: seaborn>=0.13.2
Provides-Extra: all
Requires-Dist: acoustic-toolbox>=0.1.2; extra == 'all'
Requires-Dist: mosqito>=1.2.1; extra == 'all'
Requires-Dist: numba>=0.59; extra == 'all'
Requires-Dist: scikit-maad>=1.4.3; extra == 'all'
Requires-Dist: tqdm>=4.66.5; extra == 'all'
Provides-Extra: audio
Requires-Dist: acoustic-toolbox>=0.1.2; extra == 'audio'
Requires-Dist: mosqito>=1.2.1; extra == 'audio'
Requires-Dist: numba>=0.59; extra == 'audio'
Requires-Dist: scikit-maad>=1.4.3; extra == 'audio'
Requires-Dist: tqdm>=4.66.5; extra == 'audio'
